mbSTATS/__init__.py
mbSTATS/cli.py
mbSTATS/color_pal.py
mbSTATS/data_preparation.py
mbSTATS/df_convert.py
mbSTATS/final_df_prep.py
mbSTATS/pval_calculation.py
mbSTATS/pval_plot.py
mbSTATS-0.0.2.dist-info/LICENSE
mbSTATS-0.0.2.dist-info/METADATA
mbSTATS-0.0.2.dist-info/WHEEL
mbSTATS-0.0.2.dist-info/top_level.txt
mbSTATS-0.0.2.dist-info/RECORD
