Metadata-Version: 2.1
Name: mbSTATS
Version: 0.0.2
Summary: A package for statistical analysis for processed untargeted GC/MS metabolomics data
Author: Satvik
Author-email: Satvik <f20213047@goa.bits-pilani.ac.in>
Project-URL: Homepage, https://github.com/Satvik713/mbSTATS
Classifier: Programming Language :: Python :: 3
Classifier: License :: OSI Approved :: MIT License
Classifier: Operating System :: OS Independent
Requires-Python: >=3.7
License-File: LICENSE
